glink/__init__.py
glink/__main__.py
glink/abc.py
glink/cli.py
glink/configs.py
glink/core.py
glink/entry_points_console_scripts.py
glink/errors.py
glink/utils.py
glink/provs/__init__.py
glink/provs/gist.py
glink2-0.2.1.dist-info/LICENSE
glink2-0.2.1.dist-info/METADATA
glink2-0.2.1.dist-info/WHEEL
glink2-0.2.1.dist-info/entry_points.txt
glink2-0.2.1.dist-info/top_level.txt
glink2-0.2.1.dist-info/RECORD
