Metadata-Version: 2.1
Name: glink2
Version: 0.2.1
Summary: UNKNOWN
Home-page: https://github.com/Cologler/glink-python
Author: Cologler
Author-email: skyoflw@gmail.com
License: MIT License
Platform: UNKNOWN
Classifier: Development Status :: 5 - Production/Stable
Classifier: License :: OSI Approved :: MIT License
Classifier: Programming Language :: Python :: 3.7
Classifier: Programming Language :: Python :: 3.8
Classifier: Programming Language :: Python :: 3.9
Requires-Dist: PyGithub (<2.0,>=1.53)
Requires-Dist: click-anno (<0.2.0,>=0.1.1)
Requires-Dist: click-log (<0.4.0,>=0.3.2)
Requires-Dist: filelock (<4.0.0,>=3.0.12)
Requires-Dist: requests (<3.0.0,>=2.25.0)
Requires-Dist: sqlitedict (<2.0.0,>=1.7.0)
Requires-Dist: typeguard (<3.0.0,>=2.10.0)
Requires-Dist: xdg (<6.0.0,>=5.0.1)
